bayeskmeans/__init__.py
bayeskmeans/bayes_kmeans.py
bayeskmeans/bayes_methods.py
bayeskmeans/bayes_parameters.py
bayeskmeans/bayes_visualize.py
bayeskmeans/main.py
bayesKMeans-0.3.9.dist-info/LICENSE
bayesKMeans-0.3.9.dist-info/METADATA
bayesKMeans-0.3.9.dist-info/WHEEL
bayesKMeans-0.3.9.dist-info/top_level.txt
bayesKMeans-0.3.9.dist-info/RECORD
